MANIFEST.in
README.md
setup.py
pkvenv/__init__.py
pkvenv/__main__.py
pkvenv/launch.exe.py
pkvenv/launch_gui.exe.py
pkvenv/main.py
pkvenv.egg-info/PKG-INFO
pkvenv.egg-info/SOURCES.txt
pkvenv.egg-info/dependency_links.txt
pkvenv.egg-info/entry_points.txt
pkvenv.egg-info/not-zip-safe
pkvenv.egg-info/requires.txt
pkvenv.egg-info/top_level.txt