Metadata-Version: 1.2
Name: pkvenv
Version: 0.0.7
Summary: Pack your Virtualenv to anywhere.
Home-page: https://github.com/sandin/pkvenv
Author: lds2012
Author-email: lds2012@gmail.com
License: Apache License 2.0
Platform: UNKNOWN
Requires-Python: >=3.6
